odoo/addons/stock_demand_estimate_matrix/README.rst
odoo/addons/stock_demand_estimate_matrix/__init__.py
odoo/addons/stock_demand_estimate_matrix/__manifest__.py
odoo/addons/stock_demand_estimate_matrix/i18n/it.po
odoo/addons/stock_demand_estimate_matrix/i18n/stock_demand_estimate_matrix.pot
odoo/addons/stock_demand_estimate_matrix/models/__init__.py
odoo/addons/stock_demand_estimate_matrix/models/date_range.py
odoo/addons/stock_demand_estimate_matrix/models/stock_demand_estimate.py
odoo/addons/stock_demand_estimate_matrix/readme/CONTRIBUTORS.md
odoo/addons/stock_demand_estimate_matrix/readme/DESCRIPTION.md
odoo/addons/stock_demand_estimate_matrix/readme/INSTALL.md
odoo/addons/stock_demand_estimate_matrix/readme/USAGE.md
odoo/addons/stock_demand_estimate_matrix/security/ir.model.access.csv
odoo/addons/stock_demand_estimate_matrix/static/description/icon.png
odoo/addons/stock_demand_estimate_matrix/static/description/index.html
odoo/addons/stock_demand_estimate_matrix/tests/__init__.py
odoo/addons/stock_demand_estimate_matrix/tests/test_stock_demand_estimate.py
odoo/addons/stock_demand_estimate_matrix/views/date_range.xml
odoo/addons/stock_demand_estimate_matrix/views/stock_demand_estimate_view.xml
odoo/addons/stock_demand_estimate_matrix/wizards/__init__.py
odoo/addons/stock_demand_estimate_matrix/wizards/stock_demand_estimate_sheet.py
odoo/addons/stock_demand_estimate_matrix/wizards/stock_demand_estimate_sheet_line.py
odoo/addons/stock_demand_estimate_matrix/wizards/stock_demand_estimate_wizard.py
odoo/addons/stock_demand_estimate_matrix/wizards/stock_demand_estimate_wizard_view.xml
odoo_addon_stock_demand_estimate_matrix-18.0.1.0.0.3.dist-info/METADATA
odoo_addon_stock_demand_estimate_matrix-18.0.1.0.0.3.dist-info/WHEEL
odoo_addon_stock_demand_estimate_matrix-18.0.1.0.0.3.dist-info/top_level.txt
odoo_addon_stock_demand_estimate_matrix-18.0.1.0.0.3.dist-info/RECORD
