Metadata-Version: 2.1
Name: odoo-addon-stock_demand_estimate_matrix
Version: 18.0.1.0.0.3
Requires-Python: >=3.10
Requires-Dist: odoo-addon-date_range==18.0.*
Requires-Dist: odoo-addon-stock_demand_estimate==18.0.*
Requires-Dist: odoo-addon-web_widget_x2many_2d_matrix==18.0.*
Requires-Dist: odoo==18.0.*
Summary: Allows to create demand estimates.
Home-page: https://github.com/OCA/stock-logistics-warehouse
License: AGPL-3
Author: ForgeFlow, Odoo Community Association (OCA)
Author-email: support@odoo-community.org
Classifier: Programming Language :: Python
Classifier: Framework :: Odoo
Classifier: Framework :: Odoo :: 18.0
Classifier: License :: OSI Approved :: GNU Affero General Public License v3
Classifier: Development Status :: 5 - Production/Stable
